setup.py
logger/__init__.py
logger/logger.py
py_logger.egg-info/PKG-INFO
py_logger.egg-info/SOURCES.txt
py_logger.egg-info/dependency_links.txt
py_logger.egg-info/top_level.txt