Metadata-Version: 1.0
Name: py-logger
Version: 1.0.0
Summary: Multi-instantiable logger for python projects
Home-page: http://code.google.com/p/py-logger/
Author: Alexey Loshkarev
Author-email: elf2001@gmail.com
License: GPL
Platform: UNKNOWN
Classifier: Development Status :: 5 - Production/Stable
Classifier: Intended Audience :: Developers
Classifier: License :: OSI Approved :: GNU General Public License (GPL)
Classifier: Natural Language :: English
Classifier: Programming Language :: Python
Classifier: Topic :: Software Development :: Libraries :: Python Modules
